{
  "default__test_expect_table_row_count_to_equal_other_table" : {
    "name" : "default__test_expect_table_row_count_to_equal_other_table",
    "macroType" : "expression",
    "definition" : "{{ dbt_expectations.test_equal_expression(model, \"count(*)\", compare_model = compare_model, compare_expression = \"count(*) * \" + factor | string, group_by = group_by, compare_group_by = compare_group_by, row_condition = row_condition, compare_row_condition = compare_row_condition) }}",
    "parameters" : {
      "type" : "record",
      "fields" : [ {
        "name" : "model",
        "kind" : {
          "type" : "value"
        },
        "optional" : false,
        "isWorkflowNodeConfiguration" : false,
        "isReferenced" : false
      }, {
        "name" : "compare_model",
        "kind" : {
          "type" : "value"
        },
        "optional" : false,
        "isWorkflowNodeConfiguration" : false,
        "isReferenced" : false
      }, {
        "name" : "group_by",
        "kind" : {
          "type" : "value"
        },
        "optional" : false,
        "isWorkflowNodeConfiguration" : false,
        "isReferenced" : false
      }, {
        "name" : "compare_group_by",
        "kind" : {
          "type" : "value"
        },
        "optional" : false,
        "isWorkflowNodeConfiguration" : false,
        "isReferenced" : false
      }, {
        "name" : "factor",
        "kind" : {
          "type" : "value"
        },
        "optional" : false,
        "isWorkflowNodeConfiguration" : false,
        "isReferenced" : false
      }, {
        "name" : "row_condition",
        "kind" : {
          "type" : "value"
        },
        "optional" : false,
        "isWorkflowNodeConfiguration" : false,
        "isReferenced" : false
      }, {
        "name" : "compare_row_condition",
        "kind" : {
          "type" : "value"
        },
        "optional" : false,
        "isWorkflowNodeConfiguration" : false,
        "isReferenced" : false
      } ]
    },
    "staleState" : "none"
  }
}